opendataformat/__init__.py
opendataformat/docu_odf.py
opendataformat/read_odf.py
opendataformat/write_odf.py
opendataformat/data/example_dataset.odf.zip
opendataformat/data/example_dataset_v1_0_0.zip
opendataformat/data/example_dataset_v1_1_0.odf.zip
opendataformat-1.1.0.dist-info/licenses/LICENSE
opendataformat-1.1.0.dist-info/METADATA
opendataformat-1.1.0.dist-info/WHEEL
opendataformat-1.1.0.dist-info/top_level.txt
opendataformat-1.1.0.dist-info/RECORD
