Metadata-Version: 2.4
Name: opendataformat
Version: 1.1.0
Summary: The Open Data Format (ODF) is a new, non-proprietary, multilingual, metadata enriched, and zip-compressed data format with metadata structured in the Data Documentation Initiative (DDI) Codebook standard. This package allows reading and writing of data files in the Open Data Format (ODF) in pandas, and displaying metadata in different languages. For further information on the Open Data Format, see <https://opendataformat.github.io/>.
Home-page: https://opendataformat.github.io/python-package
Author: opendataformat-team
Author-email: opendataformat-team@diw.de
Classifier: Programming Language :: Python :: 3
Classifier: License :: OSI Approved :: MIT License
Classifier: Operating System :: OS Independent
Requires-Python: >=3.6
License-File: LICENSE
Requires-Dist: pandas
Dynamic: author
Dynamic: author-email
Dynamic: classifier
Dynamic: description
Dynamic: description-content-type
Dynamic: home-page
Dynamic: license-file
Dynamic: requires-dist
Dynamic: requires-python
Dynamic: summary
